mathutils/__init__.py
mathutils/basic_ops.py
mathutils/statistics.py
mathutils_chen-0.1.0.dist-info/METADATA
mathutils_chen-0.1.0.dist-info/WHEEL
mathutils_chen-0.1.0.dist-info/top_level.txt
mathutils_chen-0.1.0.dist-info/RECORD
