Metadata-Version: 2.4
Name: mathutils_chen
Version: 0.1.0
Summary: A simple mathematics utilities library
Author-email: Your Name <your.email@example.com>
License-Expression: MIT
Project-URL: Homepage, https://github.com/yourusername/mathutils
Project-URL: Repository, https://github.com/yourusername/mathutils
Project-URL: Issues, https://github.com/yourusername/mathutils/issues
Classifier: Development Status :: 3 - Alpha
Classifier: Intended Audience :: Developers
Classifier: Operating System :: OS Independent
Classifier: Programming Language :: Python :: 3
Requires-Python: >=3.9
Requires-Dist: requests>=2.25
